CHANGELOG.txt
LICENCE.txt
MANIFEST.in
README.txt
setup.py
getip.egg-info/SOURCES.txt
getip.egg-info/dependency_links.txt
getip.egg-info/requires.txt
getip.egg-info/top_level.txt
getipinfo/__innit__.py
getipinfo.egg-info/PKG-INFO
getipinfo.egg-info/SOURCES.txt
getipinfo.egg-info/dependency_links.txt
getipinfo.egg-info/requires.txt
getipinfo.egg-info/top_level.txt