Metadata-Version: 1.1
Name: getipinfo
Version: 1.0.0
Summary: tool to get ip as well as related info
Home-page: UNKNOWN
Author: Alexandru Dumitru
Author-email: dumalex222@gmail.com
License: MIT
Keywords: ip
Platform: UNKNOWN
Classifier: Development Status :: 5 - Production/Stable
Classifier: Intended Audience :: Education
Classifier: Operating System :: Microsoft :: Windows :: Windows 10
Classifier: License :: OSI Approved :: MIT License
Classifier: Programming Language :: Python :: 3
